{
    "paragraph": "Que dites-vous?... C\u2019est inutile!        Je le sais!     Mais on ne se bat pas dans l\u2019espoir du succ\u00e8s!     Non! Non! C\u2019est bien plus beau, lorsque c\u2019est inutile!     \u2014Qu\u2019est-ce que c\u2019est que tous ceux-l\u00e0?\u2014Vous \u00eates mille?     Ah! je vous reconnais, tous mes vieux ennemis!     Le mensonge!(Il frappe de son \u00e9p\u00e9e le vide.)Tiens, tiens, ha! ha! les Compromis,          Les Pr\u00e9jug\u00e9s, les L\u00e2chet\u00e9s!...(Il frappe.)Que je pactise?     Jamais, jamais!\u2014Ah, te voil\u00e0, toi, la Sottise!     \u2014Je sais bien qu\u2019\u00e0 la fin vous me mettrez \u00e0 bas;     N\u2019importe: je me bats! je me bats! je me bats!     Oui, vous m\u2019arrachez tout, le laurier et la rose!     Arrachez! Il y a malgr\u00e9 vous quelque chose     Que j\u2019emporte, et ce soir, quand j\u2019entrerai chez Dieu,     Mon salut balaiera largement le seuil bleu.     Quelque chose que sans un pli, sans une tache,     J\u2019emporte malgr\u00e9 vous, et c\u2019est\u2014mon panache.\u201dCyrano, who under the hateful exterior of his body hid a soul so much more beautiful, is a yearner and one misunderstood, and his last triumph is that he departs, at least, with a clean shield\u2014\u201cSans un pli et sans une tache.\u201d The identification of the author with the dying Christian, who in himself is a figure but little impressive and sympathetic, expresses clearly that a sudden end is destined for her love just as for Christian\u2019s love. The tragic intermezzo with Christian, however, is played as we have seen upon a background of much wider significance, viz., the misunderstood love of Cyrano for Roxane. Therefore, the identification with Christian has only the significance of a substitute memory (\u201cdeckerinnerung\u201d), and is really intended for Cyrano. That this is just what we might expect will be seen in the further course of our analysis.",
    "metadata": "psychology_of_unconscious",
    "question": "How does the text describe Cyrano's character and his last triumph?",
    "answer": "Cyrano is described as having a soul that is beautiful even under the hateful exterior of his body, making him a yearner and someone who is misunderstood. His last triumph is that he leaves with a clean shield\u2014\u201cwithout a crease and without a stain.\u201d This indicates his unwavering integrity and honor, even in the face of adversity.",
    "question_group_id": "6e2af38c-7a88-452f-8e51-5607eb4a286f",
    "paragraph_idx": 222,
    "question_idx": 2
}